revenue_maximization_ranking/__init__.py
revenue_maximization_ranking/_types.py
revenue_maximization_ranking/cascade/__init__.py
revenue_maximization_ranking/cascade/best_x.py
revenue_maximization_ranking/cascade/dataframe.py
revenue_maximization_ranking/cascade/fixed_attention.py
revenue_maximization_ranking/cascade/revenue.py
tests/__init__.py
tests/test_cascade/__init__.py
tests/test_cascade/test_fixed_attention.py
tests/test_cascade/test_revenue.py
revenue_maximization_ranking-0.0.4.dist-info/LICENSE
revenue_maximization_ranking-0.0.4.dist-info/METADATA
revenue_maximization_ranking-0.0.4.dist-info/WHEEL
revenue_maximization_ranking-0.0.4.dist-info/top_level.txt
revenue_maximization_ranking-0.0.4.dist-info/RECORD
