Metadata-Version: 2.1
Name: revenue-maximization-ranking
Version: 0.0.4
Summary: Rankings for revenue maximization
Home-page: https://github.com/taurusongithub/revenue-maximization-ranking
Author: Nicolás Agustín Rodriguez Castro
Author-email: nicorodc@gmail.com
License: UNKNOWN
Project-URL: Bug Tracker, https://github.com/taurusongithub/revenue-maximization-ranking/issues
Platform: UNKNOWN
Classifier: Programming Language :: Python :: 3
Classifier: License :: OSI Approved :: MIT License
Classifier: Operating System :: OS Independent
Requires-Python: >=3
License-File: LICENSE
